bq_properties_creator/__init__.py
bq_properties_creator/cli.py
bq_properties_creator-0.11.0.dist-info/AUTHORS.rst
bq_properties_creator-0.11.0.dist-info/LICENSE
bq_properties_creator-0.11.0.dist-info/METADATA
bq_properties_creator-0.11.0.dist-info/WHEEL
bq_properties_creator-0.11.0.dist-info/entry_points.txt
bq_properties_creator-0.11.0.dist-info/top_level.txt
bq_properties_creator-0.11.0.dist-info/RECORD
