Metadata-Version: 2.1
Name: bq-properties-creator
Version: 0.11.0
Summary: Python code that creates properties files containing all BigQuery resources
Home-page: https://github.com/mesmacosta/bq_properties_creator
Author: Marcelo Costa
Author-email: mesmacosta@gmail.com
License: MIT license
Keywords: bq_properties_creator
Platform: UNKNOWN
Classifier: Development Status :: 2 - Pre-Alpha
Classifier: Intended Audience :: Developers
Classifier: License :: OSI Approved :: MIT License
Classifier: Natural Language :: English
Classifier: Programming Language :: Python :: 3
Classifier: Programming Language :: Python :: 3.5
Classifier: Programming Language :: Python :: 3.6
Classifier: Programming Language :: Python :: 3.7
Classifier: Programming Language :: Python :: 3.8
Requires-Python: >=3.5
Requires-Dist: Click (>=7.0)
Requires-Dist: jinja2
Requires-Dist: google-cloud-bigquery
